.gitignore
CHANGELOG.md
DEVELOP.md
Dockerfile
LICENSE.txt
Makefile
README.md
RELEASE.md
environment.yml
pyproject.toml
requirements-package.txt
requirements.txt
setup.cfg
setup.py
.github/workflows/test.yml
dsne/.DS_Store
dsne/__init__.py
dsne/_dsne.py
dsne/_generated_version.py
dsne/st_dsne.pyx
dsne/utils.py
dsne.egg-info/PKG-INFO
dsne.egg-info/SOURCES.txt
dsne.egg-info/dependency_links.txt
dsne.egg-info/not-zip-safe
dsne.egg-info/requires.txt
dsne.egg-info/top_level.txt
dsne/includes/st_dsne/compile_linux
dsne/includes/st_dsne/compile_mac
dsne/includes/st_dsne/dsne.cpp
dsne/includes/st_dsne/dsne.h
dsne/includes/st_dsne/vptree.h
dsne/tests/.DS_Store
dsne/tests/__init__.py
dsne/tests/test_import.py
dsne/tests/test_seed.py
examples/.DS_Store
examples/Pancreas.py
examples/exact_simulation.py
examples/unexact_simulation.py
examples/data/Pancreas/scvelo_pancreas_dsne_umap_stream.png
examples/data/Pancreas/scvelo_pancreas_dsne_umap_stream2.png