Metadata-Version: 2.1
Name: dsne
Version: 0.1.6
Summary: DSNE algorithms
Home-page: https://github.com/songtingstone/dsne
Maintainer: Songting Shi
Maintainer-email: songtingstone@gmail.com
License: Apache License, Version 2.0
Keywords: DSNE,algorithms,numpy,cython
Platform: UNKNOWN
Classifier: License :: OSI Approved :: Apache Software License
Classifier: Programming Language :: Python :: 3.6
Classifier: Programming Language :: Python :: 3.7
Classifier: Programming Language :: Python :: 3.8
Requires-Python: >=3.6
Provides-Extra: test
Provides-Extra: dev
